hydpy/__init__.py
hydpy/aliases.py
hydpy/config.py
hydpy/py.typed
hydpy/auxs/__init__.py
hydpy/auxs/anntools.py
hydpy/auxs/armatools.py
hydpy/auxs/calibtools.py
hydpy/auxs/interptools.py
hydpy/auxs/iuhtools.py
hydpy/auxs/networktools.py
hydpy/auxs/ppolytools.py
hydpy/auxs/quadtools.py
hydpy/auxs/roottools.py
hydpy/auxs/smoothtools.py
hydpy/auxs/statstools.py
hydpy/auxs/validtools.py
hydpy/conf/HydPyConfigBase.xsd
hydpy/conf/HydPyConfigBase.xsdt
hydpy/conf/HydPyConfigMultipleRuns.xsd
hydpy/conf/HydPyConfigSingleRun.xsd
hydpy/conf/__init__.py
hydpy/conf/a_coefficients_explicit_lobatto_sequence.npy
hydpy/conf/support_points_for_smoothpar_logistic2.npy
hydpy/core/__init__.py
hydpy/core/aliastools.py
hydpy/core/autodoctools.py
hydpy/core/auxfiletools.py
hydpy/core/devicetools.py
hydpy/core/exceptiontools.py
hydpy/core/filetools.py
hydpy/core/hydpytools.py
hydpy/core/importtools.py
hydpy/core/indextools.py
hydpy/core/itemtools.py
hydpy/core/masktools.py
hydpy/core/modeltools.py
hydpy/core/netcdftools.py
hydpy/core/objecttools.py
hydpy/core/optiontools.py
hydpy/core/parametertools.py
hydpy/core/printtools.py
hydpy/core/propertytools.py
hydpy/core/pubtools.py
hydpy/core/selectiontools.py
hydpy/core/sequencetools.py
hydpy/core/seriestools.py
hydpy/core/testtools.py
hydpy/core/timetools.py
hydpy/core/typingtools.py
hydpy/core/variabletools.py
hydpy/cythons/__init__.py
hydpy/cythons/annutils.pxd
hydpy/cythons/annutils.pyi
hydpy/cythons/annutils.pyx
hydpy/cythons/configutils.pxd
hydpy/cythons/configutils.pyi
hydpy/cythons/configutils.pyx
hydpy/cythons/interfaceutils.pxd
hydpy/cythons/interfaceutils.pyi
hydpy/cythons/interfaceutils.pyx
hydpy/cythons/interputils.pxd
hydpy/cythons/interputils.pyi
hydpy/cythons/interputils.pyx
hydpy/cythons/modelutils.py
hydpy/cythons/pointerutils.pxd
hydpy/cythons/pointerutils.pyi
hydpy/cythons/pointerutils.pyx
hydpy/cythons/ppolyutils.pxd
hydpy/cythons/ppolyutils.pyi
hydpy/cythons/ppolyutils.pyx
hydpy/cythons/quadutils.pxd
hydpy-6.1.5.dist-info/licenses/LICENSE
hydpy-6.1.5.dist-info/licenses/licenses_hydpy_installer.txt
hydpy-6.1.5.dist-info/METADATA
hydpy-6.1.5.dist-info/WHEEL
hydpy-6.1.5.dist-info/top_level.txt
hydpy-6.1.5.dist-info/RECORD
