Metadata-Version: 2.4
Name: HydPy
Version: 6.1.5
Summary: A framework for the development and application of hydrological models.
Home-page: https://github.com/hydpy-dev/hydpy
Author: HydPy Developers
Author-email: c.tyralla@bjoernsen.de
License: LGPL-3.0
Keywords: hydrology modelling water balance rainfall runoff
Classifier: Intended Audience :: Education
Classifier: Intended Audience :: End Users/Desktop
Classifier: Intended Audience :: Science/Research
Classifier: License :: OSI Approved :: GNU Lesser General Public License v3 (LGPLv3)
Classifier: Operating System :: POSIX :: Linux
Classifier: Operating System :: Microsoft :: Windows
Classifier: Programming Language :: Python :: 3.9
Classifier: Programming Language :: Python :: 3.10
Classifier: Programming Language :: Python :: 3.11
Classifier: Programming Language :: Python :: 3.12
Classifier: Programming Language :: Python :: Implementation :: CPython
Classifier: Topic :: Scientific/Engineering
Requires-Python: >=3.9
License-File: LICENSE
License-File: licenses_hydpy_installer.txt
Requires-Dist: black
Requires-Dist: click
Requires-Dist: cython
Requires-Dist: strenum; python_version < "3.11"
Requires-Dist: matplotlib
Requires-Dist: netcdf4
Requires-Dist: networkx
Requires-Dist: numpy
Requires-Dist: pandas
Requires-Dist: plotly
Requires-Dist: scipy
Requires-Dist: setuptools
Requires-Dist: typing_extensions
Requires-Dist: wrapt
Requires-Dist: xmlschema
Dynamic: author
Dynamic: author-email
Dynamic: classifier
Dynamic: description
Dynamic: home-page
Dynamic: keywords
Dynamic: license
Dynamic: license-file
Dynamic: requires-dist
Dynamic: requires-python
Dynamic: summary
